django_admin_index/__init__.py
django_admin_index/admin.py
django_admin_index/apps.py
django_admin_index/conf.py
django_admin_index/models.py
django_admin_index/translations.py
django_admin_index/utils.py
django_admin_index/locale/nl/LC_MESSAGES/django.mo
django_admin_index/locale/nl/LC_MESSAGES/django.po
django_admin_index/migrations/0001_initial.py
django_admin_index/migrations/0002_auto_20170802_1754.py
django_admin_index/migrations/0003_auto_20200724_1516.py
django_admin_index/migrations/0004_auto_20230503_0723.py
django_admin_index/migrations/0005_auto_20230503_1910.py
django_admin_index/migrations/0006_auto_20230503_1910.py
django_admin_index/migrations/__init__.py
django_admin_index/static/admin/css/admin-index.css
django_admin_index/static/admin/css/admin-index.css.map
django_admin_index/templates/admin/change_form.html
django_admin_index/templates/admin/change_list.html
django_admin_index/templates/admin/delete_confirmation.html
django_admin_index/templates/admin/delete_selected_confirmation.html
django_admin_index/templates/admin/index.html
django_admin_index/templates/admin/object_history.html
django_admin_index/templates/django_admin_index/includes/app_list.html
django_admin_index/templates/registration/password_change_done.html
django_admin_index/templates/registration/password_change_form.html
django_admin_index/templates/registration/password_reset_complete.html
django_admin_index/templates/registration/password_reset_confirm.html
django_admin_index/templates/registration/password_reset_done.html
django_admin_index/templates/registration/password_reset_form.html
django_admin_index/templatetags/__init__.py
django_admin_index/templatetags/django_admin_index.py
django_admin_index-4.0.0.dist-info/LICENSE
django_admin_index-4.0.0.dist-info/METADATA
django_admin_index-4.0.0.dist-info/WHEEL
django_admin_index-4.0.0.dist-info/top_level.txt
django_admin_index-4.0.0.dist-info/RECORD
