Metadata-Version: 2.1
Name: django-admin-index
Version: 4.0.0
Summary: Admin index for Django
Author-email: Maykin Media <support@maykinmedia.nl>
License: BSD 3-Clause License
Project-URL: Homepage, https://github.com/maykinmedia/django-admin-index
Project-URL: Bug Tracker, https://github.com/maykinmedia/django-admin-index/issues
Project-URL: Source Code, https://github.com/maykinmedia/django-admin-index
Project-URL: Changelog, https://github.com/maykinmedia/django-admin-index/blob/main/CHANGELOG.rst
Keywords: Django,index,dashboard
Classifier: Development Status :: 5 - Production/Stable
Classifier: Framework :: Django
Classifier: Framework :: Django :: 4.2
Classifier: Intended Audience :: Developers
Classifier: Operating System :: Unix
Classifier: Operating System :: MacOS
Classifier: Operating System :: Microsoft :: Windows
Classifier: Programming Language :: Python :: 3.10
Classifier: Programming Language :: Python :: 3.11
Classifier: Programming Language :: Python :: 3.12
Classifier: Topic :: Software Development :: Libraries :: Python Modules
Requires-Python: >=3.10
License-File: LICENSE
Requires-Dist: django>=4.2
Requires-Dist: django-ordered-model>=3.5
Provides-Extra: tests
Requires-Dist: pytest; extra == "tests"
Requires-Dist: pytest-django; extra == "tests"
Requires-Dist: tox; extra == "tests"
Requires-Dist: isort; extra == "tests"
Requires-Dist: black; extra == "tests"
Requires-Dist: flake8; extra == "tests"
Provides-Extra: coverage
Requires-Dist: pytest-cov; extra == "coverage"
Provides-Extra: docs
Requires-Dist: sphinx; extra == "docs"
Requires-Dist: sphinx-rtd-theme; extra == "docs"
Provides-Extra: release
Requires-Dist: bump-my-version; extra == "release"
